setup.py
djamix/__init__.py
djamix.egg-info/PKG-INFO
djamix.egg-info/SOURCES.txt
djamix.egg-info/dependency_links.txt
djamix.egg-info/top_level.txt