Metadata-Version: 1.1
Name: djamix
Version: 0.1
Summary: Faster mockups and prototypes with django-like environment. Using django in the background
Home-page: https://github.com/artcz/djamix
Author: Artur Czepiel
Author-email: czepiel.artur+djamix@gmail.com
License: MIT License
Platform: UNKNOWN
Classifier: Environment :: Web Environment
Classifier: Framework :: Django
Classifier: Intended Audience :: Developers
Classifier: License :: OSI Approved :: MIT License
Classifier: Operating System :: OS Independent
Classifier: Programming Language :: Python
Classifier: Programming Language :: Python :: 3
